mush3p/__init__.py
mush3p/boundary_conditions.py
mush3p/model/__init__.py
mush3p/model/full.py
mush3p/model/full_nonlinear_gas_fraction_solve.py
mush3p/model/incompressible.py
mush3p/model/instant.py
mush3p/model/reduced.py
mush3p/output.py
mush3p/params.py
mush3p/solver.py
mush3p/static_settings.py
mush3p-1.0.1.dist-info/LICENSE
mush3p-1.0.1.dist-info/METADATA
mush3p-1.0.1.dist-info/WHEEL
mush3p-1.0.1.dist-info/RECORD
