Metadata-Version: 2.1
Name: mush3p
Version: 1.0.1
Summary: Simulate steady solidification of a three-phase mushy layer
License: MIT
Author: Joseph Fishlock
Author-email: joseph.fishlock@physics.ox.ax.uk
Requires-Python: >=3.12,<4.0
Classifier: License :: OSI Approved :: MIT License
Classifier: Programming Language :: Python :: 3
Classifier: Programming Language :: Python :: 3.12
Requires-Dist: numpy (>=2.1,<3.0)
Requires-Dist: scipy (>=1.14,<2.0)
